partitionunity/__init__.py
partitionunity/partialunity.py
partitionunity-1.0.0.dist-info/LICENCE
partitionunity-1.0.0.dist-info/METADATA
partitionunity-1.0.0.dist-info/WHEEL
partitionunity-1.0.0.dist-info/top_level.txt
partitionunity-1.0.0.dist-info/RECORD
