Metadata-Version: 2.1
Name: partitionunity
Version: 1.0.0
Summary: Evaluate PU interpolant
Home-page: https://github.com/sandro-lancellotti/PU
Author: R. Cavoretto, A. De Rossi, S. Lancellotti, E. Perracchione
Author-email: roberto.cavoretto@unito.it, alessandra.derossi@unito.it, sandro.lancellotti@unito.it, emma.perracchione@polito.it
Classifier: Programming Language :: Python :: 3
Classifier: License :: OSI Approved :: MIT License
Classifier: Operating System :: OS Independent
Requires-Python: >=3.8
License-File: LICENCE
Requires-Dist: numpy (>=1.22.4)
Requires-Dist: scipy (>=1.8.1)
